setup.py
edina/__init__.py
edina/admin.py
edina.egg-info/PKG-INFO
edina.egg-info/SOURCES.txt
edina.egg-info/dependency_links.txt
edina.egg-info/requires.txt
edina.egg-info/top_level.txt