Metadata-Version: 1.0
Name: edina
Version: 0.4
Summary: EDINA geo python helper
Home-page: UNKNOWN
Author: George Hamilton
Author-email: george.hamilton@ed.ac.uk
License: GPL
Platform: UNKNOWN
Classifier: Development Status :: 4 - Beta
Classifier: License :: OSI Approved :: GNU General Public License (GPL)
Classifier: Operating System :: OS Independent
Classifier: Programming Language :: Python
